pypi_on_github_indexer/__init__.py
pypi_on_github_indexer/__main__.py
pypi_on_github_indexer/parser/__init__.py
pypi_on_github_indexer/parser/index_html_parser.py
pypi_on_github_indexer-0.1.1.dist-info/LICENSE
pypi_on_github_indexer-0.1.1.dist-info/METADATA
pypi_on_github_indexer-0.1.1.dist-info/WHEEL
pypi_on_github_indexer-0.1.1.dist-info/top_level.txt
pypi_on_github_indexer-0.1.1.dist-info/RECORD
