Metadata-Version: 2.1
Name: pypi-on-github-indexer
Version: 0.1.1
Summary: Proprietary package publisher to the GitHub index repository.
Home-page: https://github.com/src-d/pypi-on-github-indexer
Author: source{d}
Author-email: infrastructure@sourced.tech
License: Apache-2.0
Download-URL: https://github.com/src-d/pypi-on-github-indexer
Keywords: pypi,pip
Platform: UNKNOWN
Classifier: Development Status :: 3 - Alpha
Classifier: Environment :: Console
Classifier: Intended Audience :: Developers
Classifier: License :: OSI Approved :: Apache Software License
Classifier: Operating System :: POSIX
Classifier: Programming Language :: Python :: 3.5
Classifier: Programming Language :: Python :: 3.6
Classifier: Programming Language :: Python :: 3.7
Classifier: Topic :: Software Development :: Version Control :: Git
Requires-Dist: packaging (>=16.0)
